nimsos/__init__.py
nimsos/nimsos_modules.py
nimsos/ai_tools/ai_tool_blox.py
nimsos/ai_tools/ai_tool_pdc.py
nimsos/ai_tools/ai_tool_physbo.py
nimsos/ai_tools/ai_tool_re.py
nimsos/input_tools/preparation_input_naree.py
nimsos/input_tools/preparation_input_standard.py
nimsos/output_tools/analysis_output_naree.py
nimsos/output_tools/analysis_output_standard.py
nimsos/visualization/plot_distribution.py
nimsos/visualization/plot_history.py
nimsos/visualization/plot_phase_diagram.py
nimsos-1.0.1.dist-info/METADATA
nimsos-1.0.1.dist-info/WHEEL
nimsos-1.0.1.dist-info/top_level.txt
nimsos-1.0.1.dist-info/RECORD
